{
  "truthtable" : "11011111",
  "graph" : {"creator":"JGraphT JSON Exporter","version":"1","nodes":[{"id":"a","expression":"a","primitiveIdentifier":"","type":"INPUT"},{"id":"b","expression":"b","primitiveIdentifier":"","type":"INPUT"},{"id":"c","expression":"c","primitiveIdentifier":"","type":"INPUT"},{"id":"YFP","expression":"x | y","primitiveIdentifier":"OR2","type":"LOGIC"},{"id":"A1_AmtR","expression":"~x","primitiveIdentifier":"NOT","type":"LOGIC"},{"id":"E1_BetI","expression":"~x","primitiveIdentifier":"NOT","type":"LOGIC"},{"id":"P3_PhlF","expression":"~(x | y)","primitiveIdentifier":"NOR2","type":"LOGIC"},{"id":"S2_SrpR","expression":"~x","primitiveIdentifier":"NOT","type":"LOGIC"},{"id":"O","expression":"x","primitiveIdentifier":"","type":"OUTPUT"}],"edges":[{"id":"1","source":"a","target":"A1_AmtR","variable":"x"},{"id":"2","source":"A1_AmtR","target":"P3_PhlF","variable":"x"},{"id":"3","source":"E1_BetI","target":"P3_PhlF","variable":"y"},{"id":"4","source":"P3_PhlF","target":"S2_SrpR","variable":"x"},{"id":"5","source":"c","target":"E1_BetI","variable":"x"},{"id":"6","source":"b","target":"YFP","variable":"x"},{"id":"7","source":"S2_SrpR","target":"YFP","variable":"y"},{"id":"8","source":"YFP","target":"O","variable":"x"}]}
}